[
	{
		"name": "tScript",
		"description": "A JavaScript/TypeScript playground with zero-build step and third-party library support.",
		"link": "https://github.com/PeterKwesiAnsah/tscript",
		"date": "2025-10-17",
		"tags": ["JavaScript", "TypeScript", "ESM", "WASM", "Web Tools"]
	},
	{
		"name": "bangScript",
		"description": "A stack-based bytecode interpretor.",
		"link": "https://github.com/PeterKwesiAnsah/bangScript",
		"date": "2025-01-01",
		"tags": ["Go", "C", "VM", "Programming Language", "Systems"]
	},
	{
		"name": "hack-assembler",
		"description": "An assembler for the Hack machine (from Nand2Tetris).",
		"link": "https://github.com/PeterKwesiAnsah/hack-assembler",
		"date": "2024-08-01",
		"tags": ["C", "Assembler", "Nand2Tetris", "Low-level"]
	},
	{
		"name": "bitty",
		"description": "A BitTorrent CLI.",
		"link": "https://github.com/PeterKwesiAnsah/bitty",
		"date": "2024-05-01",
		"tags": ["Go", "Networking", "BitTorrent", "WASM"]
	},
	{
		"name": "responsively",
		"description": "Contributed bookmark features to a popular responsive design tool for web developers.",
		"link": "https://github.com/PeterKwesiAnsah/responsively",
		"date": "2023-12-01",
		"tags": ["React", "Frontend", "UX", "Web"]
	},
	{
		"name": "eslint-plugin-goodeffects",
		"description": "An open-source ESLint plugin enforcing React useEffect best practices.",
		"link": "https://github.com/PeterKwesiAnsah/eslint-plugin-goodeffects",
		"date": "2023-06-01",
		"tags": ["Open Source", "ESLint", "React", "JavaScript", "Tooling"]
	},
	{
		"name": "JSON-parser",
		"description": "A 300-line JSON parser. Handles edge cases such as nested objects and arrays.",
		"link": "https://github.com/PeterKwesiAnsah/JSON-parser",
		"date": "2023-03-01",
		"tags": ["TypeScript", "Parser", "AST", "Web Tools"]
	}
]
